neuralnets/__init__.py
neuralnets/cross_validation/__init__.py
neuralnets/cross_validation/base.py
neuralnets/cross_validation/unet_2d.py
neuralnets/data/__init__.py
neuralnets/data/base.py
neuralnets/data/datasets.py
neuralnets/networks/__init__.py
neuralnets/networks/blocks.py
neuralnets/networks/bvae.py
neuralnets/networks/cnn.py
neuralnets/networks/unet.py
neuralnets/train/__init__.py
neuralnets/train/bvae.py
neuralnets/train/dense_unet_2d.py
neuralnets/train/dense_unet_3d.py
neuralnets/train/unet_2d.py
neuralnets/train/unet_3d.py
neuralnets/util/__init__.py
neuralnets/util/augmentation.py
neuralnets/util/io.py
neuralnets/util/losses.py
neuralnets/util/tools.py
neuralnets/util/validation.py
neuralnets/util/visualization.py
neuralnets/util/numpy/__init__.py
neuralnets/util/numpy/metrics.py
neuralnets/util/torch/__init__.py
neuralnets/util/torch/metrics.py
neuralnets-1.1.9.1.dist-info/LICENSE
neuralnets-1.1.9.1.dist-info/METADATA
neuralnets-1.1.9.1.dist-info/WHEEL
neuralnets-1.1.9.1.dist-info/top_level.txt
neuralnets-1.1.9.1.dist-info/RECORD
